simdna/__init__.py
simdna/dinuc_shuffle.py
simdna/fileProcessing.py
simdna/pwm.py
simdna/simulations.py
simdna/synthetic.py
simdna/util.py
simdna/resources/HOCOMOCOv10_HUMAN_mono_homer_format_0.001.motif.gz
simdna/resources/__init__.py
simdna/resources/encode_motifs.txt.gz
simdna_dragonn-0.1.data/scripts/densityMotifSimulation.py
simdna_dragonn-0.1.data/scripts/emptyBackground.py
simdna_dragonn-0.1.data/scripts/motifGrammarSimulation.py
simdna_dragonn-0.1.dist-info/LICENSE
simdna_dragonn-0.1.dist-info/METADATA
simdna_dragonn-0.1.dist-info/WHEEL
simdna_dragonn-0.1.dist-info/top_level.txt
simdna_dragonn-0.1.dist-info/RECORD
